{
  "pnls": [
    {
      "name": "ROSE",
      "pnl": 0.0361,
      "pnl_value": 0.0013,
      "weight": 0.0089,
      "rank": 84,
      "atr": 0.109,
      "score": 2,
      "status": "o"
    },
    {
      "name": "DUSK",
      "pnl": -0.0043,
      "pnl_value": -0.0002,
      "weight": 0.0093,
      "rank": 187,
      "atr": 0.1041,
      "score": 1,
      "status": "o"
    },
    {
      "name": "GNO",
      "pnl": -0.0511,
      "pnl_value": -0.0024,
      "weight": 0.0119,
      "rank": 121,
      "atr": 0.0813,
      "score": 2,
      "status": "o"
    },
    {
      "name": "SYS",
      "pnl": -0.0583,
      "pnl_value": -0.0023,
      "weight": 0.0101,
      "rank": 145,
      "atr": 0.0955,
      "score": 2,
      "status": "o"
    },
    {
      "name": "SUSHI",
      "pnl": -0.08,
      "pnl_value": -0.0031,
      "weight": 0.01,
      "rank": 94,
      "atr": 0.0965,
      "score": 2,
      "status": "o"
    },
    {
      "name": "ZIL",
      "pnl": "-",
      "pnl_value": "-",
      "weight": "-",
      "rank": "-",
      "atr": "-",
      "score": "-",
      "status": "-"
    }
  ],
  "raw_selected": [
    {
      "name": "GNO",
      "rank": 121,
      "atr": 0.0813,
      "type": 1,
      "score": 1
    },
    {
      "name": "SYS",
      "rank": 145,
      "atr": 0.0955,
      "type": 1,
      "score": 1
    },
    {
      "name": "SUSHI",
      "rank": 94,
      "atr": 0.0965,
      "type": 1,
      "score": 1
    },
    {
      "name": "DUSK",
      "rank": 187,
      "atr": 0.1041,
      "type": 0,
      "score": 1
    },
    {
      "name": "ROSE",
      "rank": 84,
      "atr": 0.109,
      "type": 1,
      "score": 1
    }
  ],
  "summary": {
    "daily_pnl": -0.0017,
    "cum_pnl": 2.9069,
    "leverage": 0.0502,
    "atr": 0.0048,
    "marketcap_pnt": 0.0016,
    "green_marketcap_pnt": 0
  }
}