{
  "pnls": [
    {
      "name": "ADA",
      "pnl": 0.0511,
      "pnl_value": 339.0123,
      "weight": 0.1104,
      "rank": 7,
      "atr": 0.0487,
      "score": 2,
      "status": "+"
    },
    {
      "name": "ZEC",
      "pnl": 0.0374,
      "pnl_value": 189.3386,
      "weight": 0.0842,
      "rank": 72,
      "atr": 0.0638,
      "score": 2,
      "status": "o"
    },
    {
      "name": "AVAX",
      "pnl": 0.0323,
      "pnl_value": 190.39,
      "weight": 0.0981,
      "rank": 16,
      "atr": 0.0548,
      "score": 2,
      "status": "+"
    },
    {
      "name": "SOL",
      "pnl": 0.0269,
      "pnl_value": 137.8224,
      "weight": 0.0854,
      "rank": 10,
      "atr": 0.0629,
      "score": 2,
      "status": "o"
    },
    {
      "name": "BTC",
      "pnl": 0.0167,
      "pnl_value": 162.8214,
      "weight": 0.1624,
      "rank": 1,
      "atr": 0.0331,
      "score": 1,
      "status": "o"
    },
    {
      "name": "ETC",
      "pnl": 0.0131,
      "pnl_value": 78.0903,
      "weight": 0.0993,
      "rank": 24,
      "atr": 0.0541,
      "score": 2,
      "status": "+"
    },
    {
      "name": "NEAR",
      "pnl": -0.0085,
      "pnl_value": -42.3479,
      "weight": 0.0826,
      "rank": 35,
      "atr": 0.0651,
      "score": 2,
      "status": "+"
    },
    {
      "name": "MULTI",
      "pnl": -0.0168,
      "pnl_value": -94.9055,
      "weight": 0.0941,
      "rank": 191,
      "atr": 0.0571,
      "score": 2,
      "status": "+"
    },
    {
      "name": "YFI",
      "pnl": -0.0243,
      "pnl_value": -129.8829,
      "weight": 0.089,
      "rank": 125,
      "atr": 0.0604,
      "score": 2,
      "status": "o"
    },
    {
      "name": "MX",
      "pnl": -0.1835,
      "pnl_value": -1036.1736,
      "weight": 0.094,
      "rank": 162,
      "atr": 0.0572,
      "score": 2,
      "status": "+"
    },
    {
      "name": "XVS",
      "pnl": "-",
      "pnl_value": "-",
      "weight": "-",
      "rank": "-",
      "atr": "-",
      "score": "-",
      "status": "-"
    },
    {
      "name": "RNDR",
      "pnl": "-",
      "pnl_value": "-",
      "weight": "-",
      "rank": "-",
      "atr": "-",
      "score": "-",
      "status": "-"
    },
    {
      "name": "JASMY",
      "pnl": "-",
      "pnl_value": "-",
      "weight": "-",
      "rank": "-",
      "atr": "-",
      "score": "-",
      "status": "-"
    },
    {
      "name": "INJ",
      "pnl": "-",
      "pnl_value": "-",
      "weight": "-",
      "rank": "-",
      "atr": "-",
      "score": "-",
      "status": "-"
    },
    {
      "name": "AUDIO",
      "pnl": "-",
      "pnl_value": "-",
      "weight": "-",
      "rank": "-",
      "atr": "-",
      "score": "-",
      "status": "-"
    },
    {
      "name": "ACH",
      "pnl": "-",
      "pnl_value": "-",
      "weight": "-",
      "rank": "-",
      "atr": "-",
      "score": "-",
      "status": "-"
    },
    {
      "name": "BAND",
      "pnl": "-",
      "pnl_value": "-",
      "weight": "-",
      "rank": "-",
      "atr": "-",
      "score": "-",
      "status": "-"
    },
    {
      "name": "LTC",
      "pnl": "-",
      "pnl_value": "-",
      "weight": "-",
      "rank": "-",
      "atr": "-",
      "score": "-",
      "status": "-"
    }
  ],
  "raw_selected": [
    {
      "name": "BTC",
      "rank": 1,
      "atr": 0.0331,
      "type": 0,
      "score": 1
    },
    {
      "name": "ADA",
      "rank": 7,
      "atr": 0.0487,
      "type": 1,
      "score": 1
    },
    {
      "name": "ETC",
      "rank": 24,
      "atr": 0.0541,
      "type": 1,
      "score": 1
    },
    {
      "name": "AVAX",
      "rank": 16,
      "atr": 0.0548,
      "type": 1,
      "score": 1
    },
    {
      "name": "MULTI",
      "rank": 191,
      "atr": 0.0571,
      "type": 1,
      "score": 1
    },
    {
      "name": "MX",
      "rank": 162,
      "atr": 0.0572,
      "type": 1,
      "score": 1
    },
    {
      "name": "YFI",
      "rank": 125,
      "atr": 0.0604,
      "type": 1,
      "score": 1
    },
    {
      "name": "SOL",
      "rank": 10,
      "atr": 0.0629,
      "type": 1,
      "score": 1
    },
    {
      "name": "ZEC",
      "rank": 72,
      "atr": 0.0638,
      "type": 1,
      "score": 1
    },
    {
      "name": "NEAR",
      "rank": 35,
      "atr": 0.0651,
      "type": 1,
      "score": 1
    },
    {
      "name": "AUDIO",
      "rank": 122,
      "atr": 0.0745,
      "type": 0,
      "score": 1
    },
    {
      "name": "JASMY",
      "rank": 135,
      "atr": 0.0767,
      "type": 1,
      "score": 1
    },
    {
      "name": "INJ",
      "rank": 91,
      "atr": 0.0783,
      "type": 0,
      "score": 1
    },
    {
      "name": "XVS",
      "rank": 189,
      "atr": 0.0789,
      "type": 1,
      "score": 1
    },
    {
      "name": "FTM",
      "rank": 44,
      "atr": 0.0821,
      "type": 1,
      "score": 1
    },
    {
      "name": "RNDR",
      "rank": 87,
      "atr": 0.0965,
      "type": 1,
      "score": 1
    },
    {
      "name": "ACH",
      "rank": 155,
      "atr": 0.1015,
      "type": 0,
      "score": 1
    }
  ],
  "summary": {
    "daily_pnl": -0.0034,
    "cum_pnl": 59858.4884,
    "leverage": 0.9995,
    "atr": 0.0537,
    "marketcap_pnt": 0.4962,
    "green_marketcap_pnt": 0
  }
}